ecmv/__init__.py
ecmv/constants.py
ecmv/decorators.py
ecmv/errors.py
ecmv/extract.py
ecmv/features.py
ecmv/store/extract.csv
ecmv/store.py
ecmv-0.2.16.dist-info/LICENSE
ecmv-0.2.16.dist-info/METADATA
ecmv-0.2.16.dist-info/WHEEL
ecmv-0.2.16.dist-info/RECORD
