Metadata-Version: 2.1
Name: ecmv
Version: 0.2.16
Summary: Python package for the EXE3002 - Classifiers and Machine Vision written assignment
Author: JWSchaefer
Author-email: joe.w.schaefer@gmail.com
Requires-Python: >=3.12,<4.0
Classifier: Programming Language :: Python :: 3
Classifier: Programming Language :: Python :: 3.12
Requires-Dist: appdirs (>=1.4.4,<2.0.0)
Requires-Dist: numpy (>=1.26.4,<2.0.0)
Requires-Dist: pandas (>=2.2.1,<3.0.0)
Requires-Dist: pip (>=24.0,<25.0)
Requires-Dist: scikit-image (>=0.22.0,<0.23.0)
Requires-Dist: scikit-learn (>=1.4.1.post1,<2.0.0)
Requires-Dist: scipy (>=1.12.0,<2.0.0)
Requires-Dist: seaborn (>=0.13.2,<0.14.0)
Requires-Dist: tqdm (>=4.66.2,<5.0.0)
